macropragma/__init__.py
macropragma/__main__.py
macropragma/_metadata.py
macropragma/macropragma.py
macropragma-1.0.8.dist-info/LICENSE
macropragma-1.0.8.dist-info/METADATA
macropragma-1.0.8.dist-info/WHEEL
macropragma-1.0.8.dist-info/top_level.txt
macropragma-1.0.8.dist-info/RECORD
