Metadata-Version: 2.1
Name: macropragma
Version: 1.0.8
Summary: macropragma - apply macros/substitutions/modifications on top of your source code 
Home-page: https://pypi.org/project/macropragma/
Author: Jerzy Jamroz
Author-email: jerzy.jamroz@gmail.com
License: LGPL-2.1-only
Keywords: macro,pragma,macropragma,epics,database,db,substitution,template
Platform: UNKNOWN
Classifier: Programming Language :: Python :: 3
Requires-Python: >=3.0
Requires-Dist: pyyaml (>=5.0.0)
Requires-Dist: argparse (>=1.1)
